click_fuzzy/__init__.py
click_fuzzy/__version__.py
click_fuzzy/core.py
click_fuzzy/tests/__init__.py
click_fuzzy/tests/smoke.py
click_fuzzy-0.2.dist-info/LICENSE
click_fuzzy-0.2.dist-info/WHEEL
click_fuzzy-0.2.dist-info/METADATA
click_fuzzy-0.2.dist-info/RECORD
