Metadata-Version: 2.1
Name: click-fuzzy
Version: 0.2
Summary: Fuzzy command matching and aliases for click
Author-email: Amethyst Reese <amethyst@n7.gg>
Requires-Python: >=3.8
Classifier: License :: OSI Approved :: MIT License
Requires-Dist: click >= 8
Requires-Dist: editdistance >= 0.6
Requires-Dist: attribution==1.6.2 ; extra == "dev"
Requires-Dist: black==23.7.0 ; extra == "dev"
Requires-Dist: flake8==6.1.0 ; extra == "dev"
Requires-Dist: flit==3.9.0 ; extra == "dev"
Requires-Dist: mypy==1.4.1 ; extra == "dev"
Requires-Dist: ufmt==2.2.0 ; extra == "dev"
Requires-Dist: usort==1.0.6 ; extra == "dev"
Project-URL: Home, https://github.com/amyreese/click-fuzzy
Provides-Extra: dev
